{
    "private_out": {
        "DEALTCARDS": ["player_id", "cards"]
    },
    "public_out": {
        "NEWROUND": [],
        "NEWTURN": ["turn"],
        "SMALLBLIND": ["player_id", "turn_stake"],
        "BIGBLIND": ["player_id", "turn_stake"],
        "PLAYERAMAUNTTOCALL": ["player_id", "to_call"],
        "PLAYERFOLD": ["player_id"],
        "PLAYERCHECK": ["player_id"],
        "PLAYERCALL": ["player_id", "called"],
        "PLAYERRAISE": ["player_id", "raised_by"],
        "PLAYERALLIN": ["player_id", "all_in_stake"],
        "PUBLICCARDSHOW": ["player_id"],
        "DECLAREPREMATUREWINNER": ["player_id", "money_won"],
        "DECLAREFINISHEDWINNER": ["player_id", "money_won", "kickers"],
        "ROUNDFINISHED": []
    }
}